coursetempi/__cli__.py
coursetempi/__init__.py
coursetempi/_version.py
coursetempi/conf/about/coursetempi.yaml
coursetempi/py.typed
course_template_i18n-0.4.0.dist-info/LICENSE
course_template_i18n-0.4.0.dist-info/METADATA
course_template_i18n-0.4.0.dist-info/WHEEL
course_template_i18n-0.4.0.dist-info/entry_points.txt
course_template_i18n-0.4.0.dist-info/RECORD
